problem/module pipeline_register.v
module pipeline_register 
(
    parameter WIDTH = 32
)
(
    input                  clk,
    input                  rst_n,

    // Input interface
    input                  in_valid,
    output                 in_ready,
    input  [WIDTH-1:0]     in_data,

    // Output interface
    output                 out_valid,
    input                  out_ready,
    output [WIDTH-1:0]     out_data
);

    reg [WIDTH-1:0] data_q;
    reg             valid_q;

    //------------------------------------------
    // Ready/Valid Assignments
    //------------------------------------------
    assign in_ready  = ~valid_q | out_ready;
    assign out_valid = valid_q;
    assign out_data  = data_q;

    //------------------------------------------
    // Sequential Logic
    //------------------------------------------
    always @(posedge clk or negedge rst_n) begin
        if (!rst_n) begin
            valid_q <= 1'b0;
            data_q  <= {WIDTH{1'b0}};
        end
        else begin
            // Accept new data
            if (in_valid && in_ready) begin
                data_q  <= in_data;
                valid_q <= 1'b1;
            end
            // Downstream consumes data
            else if (out_ready && valid_q) begin
                valid_q <= 1'b0;
            end
        end
    end

endmodule

problem/pipeline_register_tb.v
`timescale 1ns/1ps

module pipeline_register_tb;

    parameter WIDTH = 8;

    reg clk;
    reg rst_n;

    // Input interface
    reg                  in_valid;
    wire                 in_ready;
    reg  [WIDTH-1:0]     in_data;

    // Output interface
    wire                 out_valid;
    reg                  out_ready;
    wire [WIDTH-1:0]     out_data;

    // Instantiate DUT
    pipeline_register #(.WIDTH(WIDTH)) dut (
        .clk(clk),
        .rst_n(rst_n),
        .in_valid(in_valid),
        .in_ready(in_ready),
        .in_data(in_data),
        .out_valid(out_valid),
        .out_ready(out_ready),
        .out_data(out_data)
    );


    always #5 clk = ~clk;

 
    initial begin
       
        $dumpfile("dump.vcd");
        $dumpvars(0, pipeline_register_tb);

        clk = 0;
        rst_n = 0;
        in_valid = 0;
        in_data = 0;
        out_ready = 0;

        // Reset
        #20;
        rst_n = 1;

        // Case 1: Normal transfer
        #10;
        in_valid = 1;
        in_data  = 8'hA5;
        out_ready = 1;

        #10;
        in_valid = 0;

        // Case 2: Backpressure
        #10;
        in_valid = 1;
        in_data  = 8'h3C;
        out_ready = 0;   /

        #20;             
        out_ready = 1;   
        #10;
        in_valid = 0;

        // Case 3: Continuous streaming
        #10;
        out_ready = 1;
        in_valid = 1;
        in_data  = 8'h55;

        #10;
        in_data  = 8'hAA;

        #10;
        in_data  = 8'hFF;

        #10;
        in_valid = 0;

        #30;
        $finish;
    end

endmodule

problem/dump.vcd
$date
	Thu Feb 05 19:30:22 2026
$end
$version
	Icarus Verilog
$end
$timescale
	1ps
$end
$scope module pipeline_register_tb $end
$var wire 1 ! out_valid $end
$var wire 8 " out_data [7:0] $end
$var wire 1 # in_ready $end
$var parameter 32 $ WIDTH $end
$var reg 1 % clk $end
$var reg 8 & in_data [7:0] $end
$var reg 1 ' in_valid $end
$var reg 1 ( out_ready $end
$var reg 1 ) rst_n $end
$scope module dut $end
$var wire 1 % clk $end
$var wire 8 * in_data [7:0] $end
$var wire 1 # in_ready $end
$var wire 1 ' in_valid $end
$var wire 8 + out_data [7:0] $end
$var wire 1 ( out_ready $end
$var wire 1 ! out_valid $end
$var wire 1 ) rst_n $end
$var parameter 32 , WIDTH $end
$var reg 8 - data_q [7:0] $end
$var reg 1 . valid_q $end
$upscope $end
$upscope $end
$enddefinitions $end
$comment Show the parameter values. $end
$dumpall
b1000 ,
b1000 $
$end
#0
$dumpvars
0.
b0 -
b0 +
b0 *
0)
0(
0'
b0 &
0%
1#
b0 "
0!
$end
#5000
1%
#10000
0%
#15000
1%
#20000
0%
1)
#25000
1%
#30000
0%
1(
b10100101 &
b10100101 *
1'
#35000
1!
1.
b10100101 "
b10100101 +
b10100101 -
1%
#40000
0%
0'
#45000
0!
0.
1%
#50000
0%
0(
b111100 &
b111100 *
1'
#55000
0#
1!
1.
b111100 "
b111100 +
b111100 -
1%
#60000
0%
#65000
1%
#70000
1#
0%
1(
#75000
1%
#80000
0%
0'
#85000
0!
0.
1%
#90000
0%
b1010101 &
b1010101 *
1'
#95000
1!
1.
b1010101 "
b1010101 +
b1010101 -
1%
#100000
0%
b10101010 &
b10101010 *
#105000
b10101010 "
b10101010 +
b10101010 -
1%
#110000
0%
b11111111 &
b11111111 *
#115000
b11111111 "
b11111111 +
b11111111 -
1%
#120000
0%
0'
#125000
0!
0.
1%
